LICENSE.md
MANIFEST.in
README.md
setup.cfg
setup.py
src/key_craftsman/__init__.py
src/key_craftsman/all_words.json
src/key_craftsman/key_craftsman.py
src/key_craftsman/key_qrcode.py
src/key_craftsman.egg-info/PKG-INFO
src/key_craftsman.egg-info/SOURCES.txt
src/key_craftsman.egg-info/dependency_links.txt
src/key_craftsman.egg-info/top_level.txt
tests/test_craftsman.py