Metadata-Version: 2.1
Name: key-craftsman
Version: 1.2.13
Summary: A versatile program to generate customizable passkeys to your own liking.
Home-page: https://github.com/yousefabuz17/KeyCraftsman
Download-URL: https://github.com/yousefabuz17/KeyCraftsman.git
Author: Yousef Abuzahrieh
Author-email: yousefzahrieh17@gmail.com
License: Apache Software License
Platform: Windows
Platform: Linux
Platform: MacOS
Classifier: Development Status :: 4 - Beta
Classifier: Intended Audience :: Developers
Classifier: License :: OSI Approved :: Apache Software License
Classifier: Operating System :: OS Independent
Classifier: Programming Language :: Python :: 3
Classifier: Programming Language :: Python :: 3 :: Only
Classifier: Topic :: Utilities
License-File: LICENSE.md
